isaacscript_lua.py
isaacscript_lua-1.0.4.dist-info/entry_points.txt
isaacscript_lua-1.0.4.dist-info/LICENSE
isaacscript_lua-1.0.4.dist-info/WHEEL
isaacscript_lua-1.0.4.dist-info/METADATA
isaacscript_lua-1.0.4.dist-info/RECORD
